templateMF/__init__.py
templateMF/exemplo.txt
templateMF/templateMF.md
templatemf-0.2.dist-info/entry_points.txt
templatemf-0.2.dist-info/LICENSE
templatemf-0.2.dist-info/WHEEL
templatemf-0.2.dist-info/METADATA
templatemf-0.2.dist-info/RECORD
