Metadata-Version: 2.1
Name: templateMF
Version: 0.2
Summary: An amazing flit templates package!
Author-email: yakari144 <pg50477@uminho.pt>
Classifier: License :: OSI Approved :: MIT License
Requires-Dist: argparse
